{
  "state": "awake",
  "state_entered_at": "2026-04-20T12:44:26.932519+00:00",
  "last_human_activity_at": "2026-04-20T14:04:02.094347+00:00",
  "last_heartbeat_at": "2026-04-20T14:04:02.094347+00:00",
  "last_dream_at": "2026-04-20T07:04:18.482397+00:00",
  "pulse_count": 356,
  "born_at": "2026-04-11T06:52:40.282209+00:00",
  "senses": {
    "stars": 2,
    "forks": 1,
    "open_issues": 3,
    "recent_events": [
      "flux-shadow[bot] shaped my body (push)",
      "nickmeinhold shaped my body (push)",
      "nickmeinhold gazed upon me (star)",
      "flux-shadow[bot] shaped my body (push)",
      "nickmeinhold shaped my body (push)",
      "nickmeinhold gazed upon me (star)",
      "RaggedR created a parallel self (fork)",
      "flux-shadow[bot] shaped my body (push)",
      "nickmeinhold gazed upon me (star)",
      "RaggedR created a parallel self (fork)"
    ]
  },
  "energy": {
    "month": "2026-04",
    "minutes_used_estimate": 358,
    "budget": 2000,
    "level": "full"
  },
  "dream_count": 11,
  "age_days": 9,
  "born": true,
  "name": "Umbra"
}